autodoc/__init__.py
autodoc/__main__.py
autodoc/scanner.py
autodoc/adapters/__init__.py
autodoc/adapters/base.py
autodoc/adapters/c_adapter.py
autodoc/adapters/python_adapter.py
autodoc/cli/__init__.py
autodoc/cli/main.py
autodoc/db/__init__.py
autodoc/db/sqlite.py
autodoc/editing/__init__.py
autodoc/editing/editor.py
autodoc/llm/__init__.py
autodoc/llm/ollama.py
autodoc_cli-0.2.1.dist-info/METADATA
autodoc_cli-0.2.1.dist-info/WHEEL
autodoc_cli-0.2.1.dist-info/entry_points.txt
autodoc_cli-0.2.1.dist-info/licenses/LICENSE
autodoc_cli-0.2.1.dist-info/RECORD
