Metadata-Version: 2.4
Name: autodoc-cli
Version: 0.2.1
Summary: CLI to auto-generate C doc comments using Tree-sitter and Ollama
Project-URL: Homepage, https://github.com/pierrelgol/autodoc-cli
Project-URL: Source, https://github.com/pierrelgol/autodoc-cli
Project-URL: Issues, https://github.com/pierrelgol/autodoc-cli/issues
Project-URL: Documentation, https://github.com/pierrelgol/autodoc-cli#readme
Author-email: PierreLgol <plgol.perso@gmail.com>
License: MIT
License-File: LICENSE
Keywords: c,cli,documentation,ollama,tree-sitter
Classifier: Development Status :: 4 - Beta
Classifier: Environment :: Console
Classifier: Intended Audience :: Developers
Classifier: License :: OSI Approved :: MIT License
Classifier: Operating System :: OS Independent
Classifier: Programming Language :: Python :: 3
Classifier: Programming Language :: Python :: 3.12
Classifier: Programming Language :: Python :: 3.13
Classifier: Topic :: Documentation
Classifier: Topic :: Software Development :: Code Generators
Classifier: Topic :: Software Development :: Documentation
Classifier: Topic :: Software Development :: Libraries :: Python Modules
Classifier: Topic :: Text Processing :: Markup
Classifier: Typing :: Typed
Requires-Python: >=3.12
Requires-Dist: pathspec>=0.12
Requires-Dist: requests>=2.32
Requires-Dist: tqdm>=4.66
Requires-Dist: tree-sitter-languages>=1.10.2
Requires-Dist: tree-sitter==0.20.4
Requires-Dist: typer>=0.12
Provides-Extra: dev
Requires-Dist: mypy>=1.10; extra == 'dev'
Requires-Dist: pytest-cov; extra == 'dev'
Requires-Dist: pytest>=8.2; extra == 'dev'
Requires-Dist: python-lsp-server[all]>=1.11; extra == 'dev'
Requires-Dist: ruff>=0.6; extra == 'dev'
Requires-Dist: types-requests>=2.32; extra == 'dev'
Requires-Dist: types-tree-sitter-languages; extra == 'dev'
